utf64.py
utf64-1.0.4.dist-info/WHEEL
utf64-1.0.4.dist-info/METADATA
utf64-1.0.4.dist-info/RECORD
