Metadata-Version: 2.1
Name: utf64
Version: 1.0.4
Summary: Encoder/decoder for UTF-64, a URL-safe encoding for JSONish strings
Author-email: Iain Merrick <iain@moreplease.com>
Requires-Python: >=3.3
Classifier: Programming Language :: Python :: 3
Classifier: License :: OSI Approved :: BSD License
Classifier: Operating System :: OS Independent
Project-URL: Home, https://github.com/more-please/more-stuff
